<ActorFrame InitCommand="hidden,1" OnCommand="%function(self) jug_this_chara = 2 jug_fb_add(1,jug_this_chara,self) end" ><children>

	<Layer File="_idle" OnCommand="hidden,0;x,5;effectclock,bgm" PushCommand="hidden,1;sleep,0.23;queuecommand,Idle" IdleCommand="hidden,0;" HurtCommand="stoptweening;hidden,1;" />
	<Layer File="_push" OnCommand="hidden,1;x,5;" PushCommand="hidden,0;setstate,0;sleep,0.23;queuecommand,Idle" IdleCommand="hidden,1;" HurtCommand="stoptweening;hidden,1;" />
	<Layer File="hurt" OnCommand="hidden,1;x,5;" IdleCommand="hidden,1;" PushCommand="hidden,1;" HurtCommand="hidden,0;" />
	
	<Layer File="../box" OnCommand="y,120;" />
	
	<Layer File="../arrows/4th/4th.model" InitCommand="y,120;hidden,0;" OnCommand="%function(self) jug_fb_notes[1][jug_this_chara][ jug_fb_counter[jug_this_chara] ].q4 = self end" />
	<Layer File="../arrows/8th/8th.model" InitCommand="y,120;hidden,1;" OnCommand="%function(self) jug_fb_notes[1][jug_this_chara][ jug_fb_counter[jug_this_chara] ].q8 = self end" />
	<Layer File="../arrows/16th/16th.model" InitCommand="y,120;hidden,1;" OnCommand="%function(self) jug_fb_notes[1][jug_this_chara][ jug_fb_counter[jug_this_chara] ].q16 = self end" />
	
	<Layer Type="Quad" InitCommand="hidden,1" OnCommand="%function(self) jug_fb_notes[1][jug_this_chara][ jug_fb_counter[jug_this_chara] ].aux = self end" />
	
	<!--this is really unpleasant. I will be very surprised if this works...-->
	<Layer Type="Quad" InitCommand="hidden,1" OnCommand="%function(self) jug_fb_counter[jug_this_chara] = jug_fb_counter[jug_this_chara]+1 end" />

</children></ActorFrame>